fluxburst
