Metadata-Version: 2.1
Name: flux-burst
Version: 0.0.15
Summary: Flux module that enables burstable plugins.
Home-page: https://github.com/converged-computing/flux-burst
Author: Vanessa Sochat
Author-email: vsoch@users.noreply.github.com
Maintainer: Vanessa Sochat
License: LICENSE
Keywords: cloud,flux-framework,flux,bursting
Platform: UNKNOWN
Classifier: Intended Audience :: Science/Research
Classifier: Intended Audience :: Developers
Classifier: License :: OSI Approved :: MIT License
Classifier: Programming Language :: Python
Classifier: Topic :: Software Development
Classifier: Topic :: Scientific/Engineering
Classifier: Operating System :: Unix
Classifier: Programming Language :: Python :: 3.8
Provides-Extra: all
Provides-Extra: kubernetes
License-File: LICENSE
License-File: NOTICE
